PyAnti/__init__.py
PyAnti-1.0.dist-info/LICENSE
PyAnti-1.0.dist-info/METADATA
PyAnti-1.0.dist-info/WHEEL
PyAnti-1.0.dist-info/top_level.txt
PyAnti-1.0.dist-info/RECORD
